bmatrix/__init__.py
bmatrix/__main__.py
bmatrix/geometry.py
bmatrix/geometry_test.py
bmatrix/main.py
bmatrix/particle.py
bmatrix/stage.py
broken_matrix-0.0.10.dist-info/LICENSE
broken_matrix-0.0.10.dist-info/METADATA
broken_matrix-0.0.10.dist-info/WHEEL
broken_matrix-0.0.10.dist-info/entry_points.txt
broken_matrix-0.0.10.dist-info/top_level.txt
broken_matrix-0.0.10.dist-info/RECORD
