Metadata-Version: 2.1
Name: broken-matrix
Version: 0.0.10
Summary: Broken matrix
Home-page: https://github.com/yell0w4x/broken-matrix
Author: yell0w4x
Author-email: yell0w4x@gmail.com
License: MIT
Project-URL: Bug Tracker, https://github.com/yell0w4x/broken-matrix/issues
Keywords: matrix terminal
Classifier: Programming Language :: Python :: 3
Classifier: Operating System :: OS Independent
Requires-Python: >=3.6
License-File: LICENSE
Requires-Dist: blessed ==1.20.0
Requires-Dist: six ==1.16.0
Requires-Dist: wcwidth ==0.2.13
